odoo/addons/website_sale_barcode_search/README.rst
odoo/addons/website_sale_barcode_search/__init__.py
odoo/addons/website_sale_barcode_search/__manifest__.py
odoo/addons/website_sale_barcode_search/controllers/__init__.py
odoo/addons/website_sale_barcode_search/controllers/website_sale.py
odoo/addons/website_sale_barcode_search/i18n/it.po
odoo/addons/website_sale_barcode_search/i18n/website_sale_barcode_search.pot
odoo/addons/website_sale_barcode_search/readme/CONTRIBUTORS.rst
odoo/addons/website_sale_barcode_search/readme/DESCRIPTION.rst
odoo/addons/website_sale_barcode_search/readme/USAGE.rst
odoo/addons/website_sale_barcode_search/static/description/icon.png
odoo/addons/website_sale_barcode_search/static/description/index.html
odoo14_addon_website_sale_barcode_search-14.0.1.0.1.dev4.dist-info/METADATA
odoo14_addon_website_sale_barcode_search-14.0.1.0.1.dev4.dist-info/WHEEL
odoo14_addon_website_sale_barcode_search-14.0.1.0.1.dev4.dist-info/top_level.txt
odoo14_addon_website_sale_barcode_search-14.0.1.0.1.dev4.dist-info/RECORD
