Metadata-Version: 2.1
Name: odoo14-addon-website_sale_barcode_search
Version: 14.0.1.0.1.dev4
Summary: It improve website product search adding search by barcode
Home-page: https://github.com/OCA/e-commerce
Author: Studio73, Odoo Community Association (OCA)
Author-email: support@odoo-community.org
License: AGPL-3
Classifier: Programming Language :: Python
Classifier: Framework :: Odoo
Classifier: Framework :: Odoo :: 14.0
Classifier: License :: OSI Approved :: GNU Affero General Public License v3
Requires-Python: >=3.6
Requires-Dist: odoo<14.1dev,>=14.0a
